{
  "$schema": "https://developer.microsoft.com/json-schemas/fabric/item/report/definition/visualContainer/2.8.0/schema.json",
  "name": "9438e383aa9af019606d",
  "position": {
    "x": 509.40669274742646,
    "y": 102.67081198923324,
    "z": 18000,
    "height": 40.816326530612244,
    "width": 143.67346938775509,
    "tabOrder": 15000
  },
  "visual": {
    "visualType": "textbox",
    "objects": {
      "general": [
        {
          "properties": {
            "paragraphs": [
              {
                "textRuns": [
                  {
                    "value": "Total Orders",
                    "textStyle": {
                      "fontWeight": "bold",
                      "fontFamily": "Segoe UI Semibold",
                      "fontSize": "16pt",
                      "color": "#076d22"
                    }
                  }
                ]
              }
            ]
          }
        }
      ]
    },
    "visualContainerObjects": {
      "background": [
        {
          "properties": {
            "show": {
              "expr": {
                "Literal": {
                  "Value": "false"
                }
              }
            }
          }
        }
      ]
    },
    "drillFilterOtherVisuals": true
  }
}