{
  "$schema": "https://developer.microsoft.com/json-schemas/fabric/item/report/definition/visualContainer/2.8.0/schema.json",
  "name": "1ad452b77ebb0732a789",
  "position": {
    "x": 448.90995260663504,
    "y": 145.59241706161137,
    "z": 41000,
    "height": 72.796208530805686,
    "width": 260.85308056872037,
    "tabOrder": 41000
  },
  "visual": {
    "visualType": "areaChart",
    "query": {
      "queryState": {
        "Category": {
          "projections": [
            {
              "field": {
                "Column": {
                  "Expression": {
                    "SourceRef": {
                      "Entity": "olist_orders_dataset"
                    }
                  },
                  "Property": "month"
                }
              },
              "queryRef": "olist_orders_dataset.month",
              "nativeQueryRef": "month",
              "active": true
            }
          ]
        },
        "Y": {
          "projections": [
            {
              "field": {
                "Measure": {
                  "Expression": {
                    "SourceRef": {
                      "Entity": "olist_orders_dataset"
                    }
                  },
                  "Property": "Cancel rate"
                }
              },
              "queryRef": "olist_orders_dataset.Cancel rate",
              "nativeQueryRef": "Cancel rate"
            }
          ]
        }
      }
    },
    "objects": {
      "categoryAxis": [
        {
          "properties": {
            "show": {
              "expr": {
                "Literal": {
                  "Value": "false"
                }
              }
            },
            "showAxisTitle": {
              "expr": {
                "Literal": {
                  "Value": "false"
                }
              }
            }
          }
        }
      ],
      "valueAxis": [
        {
          "properties": {
            "showAxisTitle": {
              "expr": {
                "Literal": {
                  "Value": "false"
                }
              }
            },
            "show": {
              "expr": {
                "Literal": {
                  "Value": "false"
                }
              }
            }
          }
        }
      ],
      "lineStyles": [
        {
          "properties": {
            "areaMatchStrokeColor": {
              "expr": {
                "Literal": {
                  "Value": "false"
                }
              }
            },
            "areaColor": {
              "solid": {
                "color": {
                  "expr": {
                    "Literal": {
                      "Value": "'#078A1D'"
                    }
                  }
                }
              }
            }
          }
        }
      ]
    },
    "visualContainerObjects": {
      "title": [
        {
          "properties": {
            "show": {
              "expr": {
                "Literal": {
                  "Value": "false"
                }
              }
            }
          }
        }
      ],
      "background": [
        {
          "properties": {
            "show": {
              "expr": {
                "Literal": {
                  "Value": "false"
                }
              }
            }
          }
        }
      ]
    },
    "drillFilterOtherVisuals": true
  }
}